MANIFEST.in
README.md
pyproject.toml
setup.cfg
setup.py
idi/__init__.py
idi.egg-info/PKG-INFO
idi.egg-info/SOURCES.txt
idi.egg-info/dependency_links.txt
idi.egg-info/requires.txt
idi.egg-info/top_level.txt
idi/reconstruction/__init__.py
idi/reconstruction/autocorrelate3.c
idi/reconstruction/common.py
idi/reconstruction/cpucor.py
idi/reconstruction/cpucorrad.py
idi/reconstruction/cpusimple.py
idi/reconstruction/cucor.py
idi/reconstruction/cucorrad.py
idi/reconstruction/cusimple.py
idi/reconstruction/ft.py
idi/reconstruction/hitcor.py
idi/reconstruction/hitcorrad.py
idi/reconstruction/singleshotnorm.py
idi/simulation/__init__.py
idi/simulation/common.py
idi/simulation/cpu.py
idi/simulation/cuda.py
idi/simulation/cutime.py
idi/simulation/sim.cu
idi/simulation/simobj.py
idi/simulation/simple.py
idi/simulation/simtime.cu
idi/simulation/time.py
idi/util/__init__.py
idi/util/accum.py
idi/util/datasetreader.py
idi/util/filters.py
idi/util/funchelper.py
idi/util/h5util.py
idi/util/poissondisk.py
idi/util/random.py
idi/util/submitmagic.py
tests/__init__.py
tests/test_recon.py
tests/test_sim.py
tests/test_util.py