Metadata-Version: 2.1
Name: idi
Version: 0.0.250901
Summary: idi simulation and reconstruction
Home-page: UNKNOWN
License: UNKNOWN
Platform: UNKNOWN
Requires-Python: >=3.9, <3.13
